proto_matcher/__init__.py
proto_matcher/compare/__init__.py
proto_matcher/compare/compare.py
proto_matcher/compare/compare_test.py
proto_matcher/compare/iter_util.py
proto_matcher/matcher/__init__.py
proto_matcher/matcher/matcher.py
proto_matcher/matcher/matcher_test.py
proto_matcher-0.0.3.dist-info/LICENSE
proto_matcher-0.0.3.dist-info/METADATA
proto_matcher-0.0.3.dist-info/WHEEL
proto_matcher-0.0.3.dist-info/top_level.txt
proto_matcher-0.0.3.dist-info/RECORD
