Metadata-Version: 2.1
Name: proto-matcher
Version: 0.0.3
Summary: Test matcher for protobuffer
Home-page: https://github.com/dayfine/proto-matcher
Author: dayfine
Author-email: 
License: UNKNOWN
Platform: UNKNOWN
Classifier: Programming Language :: Python :: 3
Classifier: License :: OSI Approved :: Apache Software License
Classifier: Operating System :: OS Independent
Requires-Python: >=3.7
